geneeval/.DS_Store
geneeval/__init__.py
geneeval/common/.DS_Store
geneeval/common/__init__.py
geneeval/common/data_utils.py
geneeval/main.py
geneeval-0.1.0a0.dist-info/entry_points.txt
geneeval-0.1.0a0.dist-info/LICENSE
geneeval-0.1.0a0.dist-info/WHEEL
geneeval-0.1.0a0.dist-info/METADATA
geneeval-0.1.0a0.dist-info/RECORD
